httpserver/__init__.py
httpserver/httpserver.py
httpserver-1.1.0.dist-info/METADATA
httpserver-1.1.0.dist-info/metadata.json
httpserver-1.1.0.dist-info/RECORD
httpserver-1.1.0.dist-info/entry_points.txt
httpserver-1.1.0.dist-info/DESCRIPTION.rst
httpserver-1.1.0.dist-info/WHEEL
httpserver-1.1.0.dist-info/top_level.txt
