Metadata-Version: 1.1
Name: httpserver
Version: 1.1.0
Summary: Asyncio implementation of an HTTP server
Home-page: https://github.com/thomwiggers/httpserver
Author: Thom Wiggers
Author-email: thom@thomwiggers.nl
License: BSD
Keywords: httpserver
Platform: UNKNOWN
Classifier: Development Status :: 3 - Alpha
Classifier: Intended Audience :: Developers
Classifier: License :: OSI Approved :: BSD License
Classifier: Natural Language :: English
Classifier: Programming Language :: Python :: 3
Classifier: Programming Language :: Python :: 3.4
